{
  "B1_Execute": "914824",
  "B1_Setup": "851347",
  "B2_Execute": "662134",
  "B2_Setup": "308039",
  "Battle1_Execute": "444258",
  "Battle1_Setup": "826551",
  "Battle2_Execute": "365549",
  "Battle2_Setup": "245876",
  "External_Execute": "454776",
  "External_Setup": "817285",
  "FirstBattle": "2932849",
  "Inline_Execute": "321179",
  "Inline_Setup": "227817",
  "Intermediary stuff": "45490",
  "SecondBattle": "2970899",
  "Setup 1": "1713066",
  "Setup 2": "312942",
  "Setup 3": "354272",
  "ThirdBattle": "2305465"
}